enaml_native_barcode.py
enaml_native_barcode-1.0.1.data/data/packages/enaml-native-barcode/android/build.gradle
enaml_native_barcode-1.0.1.data/data/packages/enaml-native-barcode/android/gradlew
enaml_native_barcode-1.0.1.data/data/packages/enaml-native-barcode/android/gradlew.bat
enaml_native_barcode-1.0.1.data/data/packages/enaml-native-barcode/android/proguard-rules.pro
enaml_native_barcode-1.0.1.data/data/packages/enaml-native-barcode/android/gradle/wrapper/gradle-wrapper.jar
enaml_native_barcode-1.0.1.data/data/packages/enaml-native-barcode/android/gradle/wrapper/gradle-wrapper.properties
enaml_native_barcode-1.0.1.data/data/packages/enaml-native-barcode/android/src/main/AndroidManifest.xml
enaml_native_barcode-1.0.1.data/data/packages/enaml-native-barcode/android/src/main/java/com/codelv/enamlnative/barcode/BarcodePackage.java
enaml_native_barcode-1.0.1.data/data/packages/enaml-native-barcode/src/setup.py
enaml_native_barcode-1.0.1.data/data/packages/enaml-native-barcode/src/zxing/__init__.py
enaml_native_barcode-1.0.1.data/data/packages/enaml-native-barcode/src/zxing/android/__init__.py
enaml_native_barcode-1.0.1.data/data/packages/enaml-native-barcode/src/zxing/android/android_barcode.py
enaml_native_barcode-1.0.1.data/data/packages/enaml-native-barcode/src/zxing/android/api.py
enaml_native_barcode-1.0.1.data/data/packages/enaml-native-barcode/src/zxing/android/factories.py
enaml_native_barcode-1.0.1.data/data/packages/enaml-native-barcode/src/zxing/widgets/__init__.py
enaml_native_barcode-1.0.1.data/data/packages/enaml-native-barcode/src/zxing/widgets/barcode.py
enaml_native_barcode-1.0.1.dist-info/DESCRIPTION.rst
enaml_native_barcode-1.0.1.dist-info/METADATA
enaml_native_barcode-1.0.1.dist-info/RECORD
enaml_native_barcode-1.0.1.dist-info/WHEEL
enaml_native_barcode-1.0.1.dist-info/entry_points.txt
enaml_native_barcode-1.0.1.dist-info/metadata.json
enaml_native_barcode-1.0.1.dist-info/top_level.txt
