Metadata-Version: 2.0
Name: enaml-native-barcode
Version: 1.0.1
Summary: QRCode and barcode scanning for enaml-native using zxing
Home-page: https://github.com/codelv/enaml-native-barcode
Author: CodeLV
Author-email: frmdstryr@gmail.com
License: MIT
Platform: UNKNOWN
Requires-Dist: enaml-native (>=2.11.8)
